aireview/__init__.py
aireview/ai_reviewer.py
aireview/config.py
aireview/git_handler.py
aireview/main.py
tests/__init__.py
tests/conftest.py
tests/test_ai_reviewer.py
tests/test_config.py
tests/test_git_handler.py
tests/test_main.py
aireview-1.3.dist-info/LICENSE
aireview-1.3.dist-info/METADATA
aireview-1.3.dist-info/WHEEL
aireview-1.3.dist-info/entry_points.txt
aireview-1.3.dist-info/top_level.txt
aireview-1.3.dist-info/RECORD
